libraryAbsf/__init__.py
libraryAbsf/bisextil_year.py
libraryAbsf/multplicator_table.py
libraryAbsf-0.1.0.dist-info/LICENCE.txt
libraryAbsf-0.1.0.dist-info/METADATA
libraryAbsf-0.1.0.dist-info/WHEEL
libraryAbsf-0.1.0.dist-info/top_level.txt
libraryAbsf-0.1.0.dist-info/RECORD
